proxy_crm/__init__.py
proxy_crm/exampleCase.ipynb
proxy_crm/fractionalFlow.py
proxy_crm/interwellVis.py
proxy_crm/proxy_crm_modules.py
proxy_crm/unisimCase.ipynb
proxy_crm-0.2.0.dist-info/LICENSE.md
proxy_crm-0.2.0.dist-info/METADATA
proxy_crm-0.2.0.dist-info/WHEEL
proxy_crm-0.2.0.dist-info/RECORD
